flask_route_builder
