Metadata-Version: 1.1
Name: Flask-RouteBuilder
Version: 0.5
Summary: Blueprint route builder for flask
Home-page: https://github.com/apecnascimento/Flask-RouterBuilder
Author: apecnascimento
Author-email: apecnascimento@gmail.com
License: MIT
Platform: any
Classifier: Environment :: Web Environment
Classifier: Intended Audience :: Developers
Classifier: License :: OSI Approved :: MIT License
Classifier: Operating System :: OS Independent
Classifier: Programming Language :: Python
Classifier: Topic :: Internet :: WWW/HTTP :: Dynamic Content
Classifier: Topic :: Software Development :: Libraries :: Python Modules
